dm_robotics/moma/__init__.py
dm_robotics/moma/action_spaces.py
dm_robotics/moma/action_spaces_test.py
dm_robotics/moma/base_task.py
dm_robotics/moma/base_task_test.py
dm_robotics/moma/effector.py
dm_robotics/moma/entity_composer.py
dm_robotics/moma/entity_initializer.py
dm_robotics/moma/initializer.py
dm_robotics/moma/moma_option.py
dm_robotics/moma/moma_option_test.py
dm_robotics/moma/prop.py
dm_robotics/moma/robot.py
dm_robotics/moma/run_tests.py
dm_robotics/moma/scene_initializer.py
dm_robotics/moma/sensor.py
dm_robotics/moma/subtask_env.py
dm_robotics/moma/subtask_env_builder.py
dm_robotics/moma/subtask_env_test.py
dm_robotics/moma/subtask_test.py
dm_robotics/moma/effectors/arm_effector.py
dm_robotics/moma/effectors/arm_effector_test.py
dm_robotics/moma/effectors/cartesian_4d_velocity_effector.py
dm_robotics/moma/effectors/cartesian_4d_velocity_effector_test.py
dm_robotics/moma/effectors/cartesian_6d_velocity_effector.py
dm_robotics/moma/effectors/cartesian_6d_velocity_effector_test.py
dm_robotics/moma/effectors/constrained_actions_effectors.py
dm_robotics/moma/effectors/constrained_actions_effectors_test.py
dm_robotics/moma/effectors/default_gripper_effector.py
dm_robotics/moma/effectors/min_max_effector.py
dm_robotics/moma/effectors/min_max_effector_test.py
dm_robotics/moma/effectors/mujoco_actuation.py
dm_robotics/moma/effectors/test_utils.py
dm_robotics/moma/models/types.py
dm_robotics/moma/models/utils.py
dm_robotics/moma/models/arenas/empty.py
dm_robotics/moma/models/arenas/empty_test.py
dm_robotics/moma/models/arenas/empty_assets/arena.xml
dm_robotics/moma/models/end_effectors/robot_hands/robot_hand.py
dm_robotics/moma/models/end_effectors/robot_hands/robotiq_2f85.py
dm_robotics/moma/models/end_effectors/robot_hands/robotiq_2f85_constants.py
dm_robotics/moma/models/end_effectors/robot_hands/robotiq_2f85_test.py
dm_robotics/moma/models/end_effectors/wrist_sensors/robotiq_fts300.py
dm_robotics/moma/models/end_effectors/wrist_sensors/robotiq_fts300.xml
dm_robotics_moma-0.10.0.dist-info/METADATA
dm_robotics_moma-0.10.0.dist-info/WHEEL
dm_robotics_moma-0.10.0.dist-info/top_level.txt
dm_robotics_moma-0.10.0.dist-info/zip-safe
dm_robotics_moma-0.10.0.dist-info/RECORD
